xupy/__init__.py
xupy/__version__.py
xupy/_core.py
xupy/py.typed
xupy/typings.py
xupy/_cupy_install/__check_availability__.py
xupy/_cupy_install/__init__.py
xupy/_cupy_install/__install_cupy__.py
xupy/ma/__init__.py
xupy/ma/core.py
xupy/ma/extras.py
xupy-1.5.1.dist-info/licenses/LICENSE
xupy-1.5.1.dist-info/METADATA
xupy-1.5.1.dist-info/WHEEL
xupy-1.5.1.dist-info/top_level.txt
xupy-1.5.1.dist-info/RECORD
