Metadata-Version: 2.4
Name: XuPy
Version: 1.5.1
Summary: GPU Accelerated masked arrays with automatic handling of CPU and GPU arrays.
Author: Pietro Ferraiuolo
Author-email: Pietro Ferraiuolo <pietro.ferraiuolo@inaf.it>
License-Expression: MIT
Project-URL: Homepage, https://github.com/pietroferraiuolo/XuPy
Requires-Python: >=3.10
License-File: LICENSE
Requires-Dist: numpy
Dynamic: author
Dynamic: license-file
Dynamic: requires-python
